roses/__init__.py
roses/effect_size/__init__.py
roses/effect_size/vargha_delaney.py
roses/effect_size/test/__init__.py
roses/effect_size/test/vargha_delaney_test.py
roses/statistical_test/__init__.py
roses/statistical_test/friedman.py
roses/statistical_test/kruskal_wallis.py
roses/statistical_test/test/__init__.py
roses/statistical_test/test/friedman_test.py
roses/statistical_test/test/kruskal_wallis_test.py
roses/utils/__init__.py
roses/utils/r_cheatsets.py
roses-0.3.9.dist-info/LICENSE
roses-0.3.9.dist-info/METADATA
roses-0.3.9.dist-info/WHEEL
roses-0.3.9.dist-info/top_level.txt
roses-0.3.9.dist-info/RECORD
