Metadata-Version: 2.1
Name: roses
Version: 0.3.9
Summary: ROSES (R pythOn Statistical tEstS) is a package to use statistical tests from R to Python
Home-page: https://github.com/jacksonpradolima/roses
Author: Jackson Antonio do Prado Lima
Author-email: jacksonpradolima@gmail.com
Maintainer: Jackson Antonio do Prado Lima
Maintainer-email: jacksonpradolima@gmail.com
License: MIT
Platform: UNKNOWN
Classifier: Programming Language :: Python :: 3.6
Classifier: Operating System :: OS Independent
Classifier: License :: OSI Approved :: MIT License
Classifier: Development Status :: 3 - Alpha
Classifier: Intended Audience :: Science/Research
Requires-Dist: pandas (>=0.23.4)
Requires-Dist: scipy (>=1.1.0)
Requires-Dist: numpy (>=1.15.2)
Requires-Dist: seaborn (>=0.9.0)
Requires-Dist: pingouin (>=0.2.2)
Requires-Dist: matplotlib (>=3.0.2)
Requires-Dist: tzlocal (==1.5.1)
Requires-Dist: rpy2 (==3.4.2)
